{
    "components": [
        {
            "bom-ref": "BomRef.081197622361876.07847623696327899",
            "name": ".python-rundeps",
            "type": "library",
            "version": "20211116.192321"
        },
        {
            "bom-ref": "BomRef.5141660072965649.3699486783653181",
            "name": "9db36492-9350-4ef5-bf2c-f7adb59b7581",
            "type": "library",
            "version": "unknown"
        },
        {
            "bom-ref": "BomRef.5901078031865207.6037685478320828",
            "name": "alpine",
            "type": "library",
            "version": "3.13.7"
        },
        {
            "bom-ref": "BomRef.5586888359751878.9725423799658867",
            "name": "alpine-baselayout",
            "type": "library",
            "version": "3.2.0-r8"
        },
        {
            "bom-ref": "BomRef.2050450682792454.7592482488013546",
            "name": "alpine-keys",
            "type": "library",
            "version": "2.4-r0"
        },
        {
            "bom-ref": "BomRef.7869579704846947.1023882786643292",
            "name": "apk-tools",
            "type": "library",
            "version": "2.12.7-r0"
        },
        {
            "bom-ref": "BomRef.4877455487621799.3904188770970878",
            "name": "busybox",
            "type": "library",
            "version": "1.32.1-r7"
        },
        {
            "bom-ref": "BomRef.838074930634034.42059493661882663",
            "name": "ca-certificates",
            "type": "library",
            "version": "20191127-r5"
        },
        {
            "bom-ref": "BomRef.15590422001138926.33314305736091976",
            "name": "ca-certificates-bundle",
            "type": "library",
            "version": "20191127-r5"
        },
        {
            "bom-ref": "BomRef.5168904474060076.9282262026894721",
            "name": "expat",
            "type": "library",
            "version": "2.2.10-r1"
        },
        {
            "bom-ref": "BomRef.5680039937275911.8544405151074901",
            "name": "gdbm",
            "type": "library",
            "version": "1.19-r0"
        },
        {
            "bom-ref": "BomRef.8630801367108792.1892625311989964",
            "name": "keyutils-libs",
            "type": "library",
            "version": "1.6.3-r0"
        },
        {
            "bom-ref": "BomRef.8477587043659347.6881937196199926",
            "name": "krb5-conf",
            "type": "library",
            "version": "1.0-r2"
        },
        {
            "bom-ref": "BomRef.6984390864616157.0496418829137677",
            "name": "krb5-libs",
            "type": "library",
            "version": "1.18.4-r0"
        },
        {
            "bom-ref": "BomRef.3963104708989147.7551625894951668",
            "name": "libbz2",
            "type": "library",
            "version": "1.0.8-r1"
        },
        {
            "bom-ref": "BomRef.9850478351979907.715715541845993",
            "name": "libc-utils",
            "type": "library",
            "version": "0.7.2-r3"
        },
        {
            "bom-ref": "BomRef.2710744565468981.12582494138113032",
            "name": "libcom_err",
            "type": "library",
            "version": "1.45.7-r0"
        },
        {
            "bom-ref": "BomRef.6903911578053002.657428990851039",
            "name": "libcrypto1.1",
            "type": "library",
            "version": "1.1.1l-r0"
        },
        {
            "bom-ref": "BomRef.4832505329874335.6288436168291416",
            "name": "libffi",
            "type": "library",
            "version": "3.3-r2"
        },
        {
            "bom-ref": "BomRef.5037432870424303.11657544211931403",
            "name": "libintl",
            "type": "library",
            "version": "0.20.2-r2"
        },
        {
            "bom-ref": "BomRef.8971233256623051.8081998034750124",
            "name": "libnsl",
            "type": "library",
            "version": "1.3.0-r0"
        },
        {
            "bom-ref": "BomRef.11095847028721362.9280125835563086",
            "name": "libssl1.1",
            "type": "library",
            "version": "1.1.1l-r0"
        },
        {
            "bom-ref": "BomRef.5268057574991246.375985914364791",
            "name": "libtirpc",
            "type": "library",
            "version": "1.3.1-r0"
        },
        {
            "bom-ref": "BomRef.6205154887666632.028125643149925716",
            "name": "libtirpc-conf",
            "type": "library",
            "version": "1.3.1-r0"
        },
        {
            "bom-ref": "BomRef.0874174963779919.29333377268929073",
            "name": "libtls-standalone",
            "type": "library",
            "version": "2.9.1-r1"
        },
        {
            "bom-ref": "BomRef.4532222517812978.4933152477393583",
            "name": "libuuid",
            "type": "library",
            "version": "2.36.1-r1"
        },
        {
            "bom-ref": "BomRef.9267934744009522.5041900529321339",
            "name": "libverto",
            "type": "library",
            "version": "0.3.1-r1"
        },
        {
            "bom-ref": "BomRef.09221013780117926.9855021864385045",
            "name": "musl",
            "type": "library",
            "version": "1.2.2-r1"
        },
        {
            "bom-ref": "BomRef.6306623754470432.25514590848309016",
            "name": "musl-utils",
            "type": "library",
            "version": "1.2.2-r1"
        },
        {
            "bom-ref": "BomRef.36958564572688757.74714478434708",
            "name": "ncurses-libs",
            "type": "library",
            "version": "6.2_p20210109-r0"
        },
        {
            "bom-ref": "BomRef.10064260186945573.9295742038753935",
            "name": "ncurses-terminfo-base",
            "type": "library",
            "version": "6.2_p20210109-r0"
        },
        {
            "bom-ref": "BomRef.07070007843852588.7918634161820075",
            "name": "pip",
            "type": "library",
            "version": "21.2.4"
        },
        {
            "bom-ref": "BomRef.10845249786757905.6295631455225235",
            "name": "pkg:apk/alpine/.python-rundeps@20211116.192321?arch=noarch&distro=3.13.7",
            "type": "library",
            "version": "unknown"
        },
        {
            "bom-ref": "BomRef.8868788744703106.4612855729544324",
            "name": "pkg:apk/alpine/alpine-baselayout@3.2.0-r8?arch=x86_64&distro=3.13.7",
            "type": "library",
            "version": "unknown"
        },
        {
            "bom-ref": "BomRef.11720920793702028.5784137703747054",
            "name": "pkg:apk/alpine/alpine-keys@2.4-r0?arch=x86_64&distro=3.13.7",
            "type": "library",
            "version": "unknown"
        },
        {
            "bom-ref": "BomRef.13926784826767413.5376780774867812",
            "name": "pkg:apk/alpine/apk-tools@2.12.7-r0?arch=x86_64&distro=3.13.7",
            "type": "library",
            "version": "unknown"
        },
        {
            "bom-ref": "BomRef.48021076054245493.4527105648709856",
            "name": "pkg:apk/alpine/busybox@1.32.1-r7?arch=x86_64&distro=3.13.7",
            "type": "library",
            "version": "unknown"
        },
        {
            "bom-ref": "BomRef.39561889060366373.5619203381473463",
            "name": "pkg:apk/alpine/ca-certificates-bundle@20191127-r5?arch=x86_64&distro=3.13.7",
            "type": "library",
            "version": "unknown"
        },
        {
            "bom-ref": "BomRef.2763911425812726.723608253030919",
            "name": "pkg:apk/alpine/ca-certificates@20191127-r5?arch=x86_64&distro=3.13.7",
            "type": "library",
            "version": "unknown"
        },
        {
            "bom-ref": "BomRef.1435770486666108.2777738060654541",
            "name": "pkg:apk/alpine/expat@2.2.10-r1?arch=x86_64&distro=3.13.7",
            "type": "library",
            "version": "unknown"
        },
        {
            "bom-ref": "BomRef.9442136822017865.15656170642622735",
            "name": "pkg:apk/alpine/gdbm@1.19-r0?arch=x86_64&distro=3.13.7",
            "type": "library",
            "version": "unknown"
        },
        {
            "bom-ref": "BomRef.4197334068222732.17908345615811538",
            "name": "pkg:apk/alpine/keyutils-libs@1.6.3-r0?arch=x86_64&distro=3.13.7",
            "type": "library",
            "version": "unknown"
        },
        {
            "bom-ref": "BomRef.8390931211341693.7571211030066881",
            "name": "pkg:apk/alpine/krb5-conf@1.0-r2?arch=x86_64&distro=3.13.7",
            "type": "library",
            "version": "unknown"
        },
        {
            "bom-ref": "BomRef.8528172910485332.8058182491224959",
            "name": "pkg:apk/alpine/krb5-libs@1.18.4-r0?arch=x86_64&distro=3.13.7",
            "type": "library",
            "version": "unknown"
        },
        {
            "bom-ref": "BomRef.9200341786545455.085577551566967",
            "name": "pkg:apk/alpine/libbz2@1.0.8-r1?arch=x86_64&distro=3.13.7",
            "type": "library",
            "version": "unknown"
        },
        {
            "bom-ref": "BomRef.933747057254292.192623378477903",
            "name": "pkg:apk/alpine/libc-utils@0.7.2-r3?arch=x86_64&distro=3.13.7",
            "type": "library",
            "version": "unknown"
        },
        {
            "bom-ref": "BomRef.4526228399758472.040031838567478606",
            "name": "pkg:apk/alpine/libcom_err@1.45.7-r0?arch=x86_64&distro=3.13.7",
            "type": "library",
            "version": "unknown"
        },
        {
            "bom-ref": "BomRef.23781215093069963.10287818011383387",
            "name": "pkg:apk/alpine/libcrypto1.1@1.1.1l-r0?arch=x86_64&distro=3.13.7",
            "type": "library",
            "version": "unknown"
        },
        {
            "bom-ref": "BomRef.00970284391705556.8624783706278352",
            "name": "pkg:apk/alpine/libffi@3.3-r2?arch=x86_64&distro=3.13.7",
            "type": "library",
            "version": "unknown"
        },
        {
            "bom-ref": "BomRef.6278394610686211.26598005540029945",
            "name": "pkg:apk/alpine/libintl@0.20.2-r2?arch=x86_64&distro=3.13.7",
            "type": "library",
            "version": "unknown"
        },
        {
            "bom-ref": "BomRef.9836932812695569.04655833901226114",
            "name": "pkg:apk/alpine/libnsl@1.3.0-r0?arch=x86_64&distro=3.13.7",
            "type": "library",
            "version": "unknown"
        },
        {
            "bom-ref": "BomRef.8318475582977882.501833798723593",
            "name": "pkg:apk/alpine/libssl1.1@1.1.1l-r0?arch=x86_64&distro=3.13.7",
            "type": "library",
            "version": "unknown"
        },
        {
            "bom-ref": "BomRef.178845208752631.3390410028462517",
            "name": "pkg:apk/alpine/libtirpc-conf@1.3.1-r0?arch=x86_64&distro=3.13.7",
            "type": "library",
            "version": "unknown"
        },
        {
            "bom-ref": "BomRef.9745197131663971.08089368020740051",
            "name": "pkg:apk/alpine/libtirpc@1.3.1-r0?arch=x86_64&distro=3.13.7",
            "type": "library",
            "version": "unknown"
        },
        {
            "bom-ref": "BomRef.19998005897320248.321710953977963",
            "name": "pkg:apk/alpine/libtls-standalone@2.9.1-r1?arch=x86_64&distro=3.13.7",
            "type": "library",
            "version": "unknown"
        },
        {
            "bom-ref": "BomRef.7482827468261886.5428181743248389",
            "name": "pkg:apk/alpine/libuuid@2.36.1-r1?arch=x86_64&distro=3.13.7",
            "type": "library",
            "version": "unknown"
        },
        {
            "bom-ref": "BomRef.41339104680807603.9148211156000156",
            "name": "pkg:apk/alpine/libverto@0.3.1-r1?arch=x86_64&distro=3.13.7",
            "type": "library",
            "version": "unknown"
        },
        {
            "bom-ref": "BomRef.29585796896308225.4011539855903097",
            "name": "pkg:apk/alpine/musl-utils@1.2.2-r1?arch=x86_64&distro=3.13.7",
            "type": "library",
            "version": "unknown"
        },
        {
            "bom-ref": "BomRef.5263196169837733.42411244869411713",
            "name": "pkg:apk/alpine/musl@1.2.2-r1?arch=x86_64&distro=3.13.7",
            "type": "library",
            "version": "unknown"
        },
        {
            "bom-ref": "BomRef.0354376712177793.31913294961590466",
            "name": "pkg:apk/alpine/ncurses-libs@6.2_p20210109-r0?arch=x86_64&distro=3.13.7",
            "type": "library",
            "version": "unknown"
        },
        {
            "bom-ref": "BomRef.06792922252167455.1234226959017205",
            "name": "pkg:apk/alpine/ncurses-terminfo-base@6.2_p20210109-r0?arch=x86_64&distro=3.13.7",
            "type": "library",
            "version": "unknown"
        },
        {
            "bom-ref": "BomRef.09217663430725431.43424391762302905",
            "name": "pkg:apk/alpine/readline@8.1.0-r0?arch=x86_64&distro=3.13.7",
            "type": "library",
            "version": "unknown"
        },
        {
            "bom-ref": "BomRef.76708726141654.15277658916071246",
            "name": "pkg:apk/alpine/scanelf@1.2.8-r0?arch=x86_64&distro=3.13.7",
            "type": "library",
            "version": "unknown"
        },
        {
            "bom-ref": "BomRef.24798322325711852.3170009239331941",
            "name": "pkg:apk/alpine/sqlite-libs@3.34.1-r0?arch=x86_64&distro=3.13.7",
            "type": "library",
            "version": "unknown"
        },
        {
            "bom-ref": "BomRef.846541610123664.047608927424914405",
            "name": "pkg:apk/alpine/ssl_client@1.32.1-r7?arch=x86_64&distro=3.13.7",
            "type": "library",
            "version": "unknown"
        },
        {
            "bom-ref": "BomRef.9447022936118712.9775926813827027",
            "name": "pkg:apk/alpine/tzdata@2021e-r0?arch=x86_64&distro=3.13.7",
            "type": "library",
            "version": "unknown"
        },
        {
            "bom-ref": "BomRef.12382043987595048.4276140553727368",
            "name": "pkg:apk/alpine/xz-libs@5.2.5-r0?arch=x86_64&distro=3.13.7",
            "type": "library",
            "version": "unknown"
        },
        {
            "bom-ref": "BomRef.9853106168035626.6743913207886603",
            "name": "pkg:apk/alpine/zlib@1.2.11-r3?arch=x86_64&distro=3.13.7",
            "type": "library",
            "version": "unknown"
        },
        {
            "bom-ref": "BomRef.04522789956784956.23901553539873766",
            "name": "pkg:oci/python@sha256%3Aa7cbd1e7784a35a098cedbc8681b790d35ff6030a5e13f043185e2465003a040?arch=amd64&repository_url=index.docker.io%2Flibrary%2Fpython",
            "type": "library",
            "version": "unknown"
        },
        {
            "bom-ref": "BomRef.40619986198946834.6387220079417574",
            "name": "pkg:pypi/pip@21.2.4",
            "type": "library",
            "version": "unknown"
        },
        {
            "bom-ref": "BomRef.5125431464776198.628013498778307",
            "name": "pkg:pypi/setuptools@57.5.0",
            "type": "library",
            "version": "unknown"
        },
        {
            "bom-ref": "BomRef.8432079752355995.9505224513071566",
            "name": "pkg:pypi/wheel@0.37.0",
            "type": "library",
            "version": "unknown"
        },
        {
            "bom-ref": "BomRef.5115547654874881.05707202961673019",
            "name": "readline",
            "type": "library",
            "version": "8.1.0-r0"
        },
        {
            "bom-ref": "BomRef.12865289530354063.7409058385801865",
            "name": "scanelf",
            "type": "library",
            "version": "1.2.8-r0"
        },
        {
            "bom-ref": "BomRef.6625159859935216.6699891159503086",
            "name": "setuptools",
            "type": "library",
            "version": "57.5.0"
        },
        {
            "bom-ref": "BomRef.8848340812693124.310430583445651",
            "name": "sqlite-libs",
            "type": "library",
            "version": "3.34.1-r0"
        },
        {
            "bom-ref": "BomRef.39058681752921864.4965611636797469",
            "name": "ssl_client",
            "type": "library",
            "version": "1.32.1-r7"
        },
        {
            "bom-ref": "BomRef.17717660968561055.7017201271770461",
            "name": "tzdata",
            "type": "library",
            "version": "2021e-r0"
        },
        {
            "bom-ref": "BomRef.7059293712872471.25201883431785255",
            "name": "wheel",
            "type": "library",
            "version": "0.37.0"
        },
        {
            "bom-ref": "BomRef.886306838997562.8658417058213653",
            "name": "xz-libs",
            "type": "library",
            "version": "5.2.5-r0"
        },
        {
            "bom-ref": "BomRef.4395110251636358.5300268735903221",
            "name": "zlib",
            "type": "library",
            "version": "1.2.11-r3"
        }
    ],
    "dependencies": [
        {
            "ref": "BomRef.5141660072965649.3699486783653181"
        },
        {
            "ref": "BomRef.10845249786757905.6295631455225235"
        },
        {
            "ref": "BomRef.8868788744703106.4612855729544324"
        },
        {
            "ref": "BomRef.11720920793702028.5784137703747054"
        },
        {
            "ref": "BomRef.13926784826767413.5376780774867812"
        },
        {
            "ref": "BomRef.48021076054245493.4527105648709856"
        },
        {
            "ref": "BomRef.39561889060366373.5619203381473463"
        },
        {
            "ref": "BomRef.2763911425812726.723608253030919"
        },
        {
            "ref": "BomRef.1435770486666108.2777738060654541"
        },
        {
            "ref": "BomRef.9442136822017865.15656170642622735"
        },
        {
            "ref": "BomRef.4197334068222732.17908345615811538"
        },
        {
            "ref": "BomRef.8390931211341693.7571211030066881"
        },
        {
            "ref": "BomRef.8528172910485332.8058182491224959"
        },
        {
            "ref": "BomRef.9200341786545455.085577551566967"
        },
        {
            "ref": "BomRef.933747057254292.192623378477903"
        },
        {
            "ref": "BomRef.4526228399758472.040031838567478606"
        },
        {
            "ref": "BomRef.23781215093069963.10287818011383387"
        },
        {
            "ref": "BomRef.00970284391705556.8624783706278352"
        },
        {
            "ref": "BomRef.6278394610686211.26598005540029945"
        },
        {
            "ref": "BomRef.9836932812695569.04655833901226114"
        },
        {
            "ref": "BomRef.8318475582977882.501833798723593"
        },
        {
            "ref": "BomRef.178845208752631.3390410028462517"
        },
        {
            "ref": "BomRef.9745197131663971.08089368020740051"
        },
        {
            "ref": "BomRef.19998005897320248.321710953977963"
        },
        {
            "ref": "BomRef.7482827468261886.5428181743248389"
        },
        {
            "ref": "BomRef.41339104680807603.9148211156000156"
        },
        {
            "ref": "BomRef.29585796896308225.4011539855903097"
        },
        {
            "ref": "BomRef.5263196169837733.42411244869411713"
        },
        {
            "ref": "BomRef.0354376712177793.31913294961590466"
        },
        {
            "ref": "BomRef.06792922252167455.1234226959017205"
        },
        {
            "ref": "BomRef.09217663430725431.43424391762302905"
        },
        {
            "ref": "BomRef.76708726141654.15277658916071246"
        },
        {
            "ref": "BomRef.24798322325711852.3170009239331941"
        },
        {
            "ref": "BomRef.846541610123664.047608927424914405"
        },
        {
            "ref": "BomRef.9447022936118712.9775926813827027"
        },
        {
            "ref": "BomRef.12382043987595048.4276140553727368"
        },
        {
            "ref": "BomRef.9853106168035626.6743913207886603"
        },
        {
            "ref": "BomRef.04522789956784956.23901553539873766"
        },
        {
            "ref": "BomRef.40619986198946834.6387220079417574"
        },
        {
            "ref": "BomRef.5125431464776198.628013498778307"
        },
        {
            "ref": "BomRef.8432079752355995.9505224513071566"
        },
        {
            "ref": "BomRef.081197622361876.07847623696327899"
        },
        {
            "ref": "BomRef.5901078031865207.6037685478320828"
        },
        {
            "ref": "BomRef.5586888359751878.9725423799658867"
        },
        {
            "ref": "BomRef.2050450682792454.7592482488013546"
        },
        {
            "ref": "BomRef.7869579704846947.1023882786643292"
        },
        {
            "ref": "BomRef.4877455487621799.3904188770970878"
        },
        {
            "ref": "BomRef.838074930634034.42059493661882663"
        },
        {
            "ref": "BomRef.15590422001138926.33314305736091976"
        },
        {
            "ref": "BomRef.5168904474060076.9282262026894721"
        },
        {
            "ref": "BomRef.5680039937275911.8544405151074901"
        },
        {
            "ref": "BomRef.8630801367108792.1892625311989964"
        },
        {
            "ref": "BomRef.8477587043659347.6881937196199926"
        },
        {
            "ref": "BomRef.6984390864616157.0496418829137677"
        },
        {
            "ref": "BomRef.3963104708989147.7551625894951668"
        },
        {
            "ref": "BomRef.9850478351979907.715715541845993"
        },
        {
            "ref": "BomRef.2710744565468981.12582494138113032"
        },
        {
            "ref": "BomRef.6903911578053002.657428990851039"
        },
        {
            "ref": "BomRef.4832505329874335.6288436168291416"
        },
        {
            "ref": "BomRef.5037432870424303.11657544211931403"
        },
        {
            "ref": "BomRef.8971233256623051.8081998034750124"
        },
        {
            "ref": "BomRef.11095847028721362.9280125835563086"
        },
        {
            "ref": "BomRef.5268057574991246.375985914364791"
        },
        {
            "ref": "BomRef.6205154887666632.028125643149925716"
        },
        {
            "ref": "BomRef.0874174963779919.29333377268929073"
        },
        {
            "ref": "BomRef.4532222517812978.4933152477393583"
        },
        {
            "ref": "BomRef.9267934744009522.5041900529321339"
        },
        {
            "ref": "BomRef.09221013780117926.9855021864385045"
        },
        {
            "ref": "BomRef.6306623754470432.25514590848309016"
        },
        {
            "ref": "BomRef.36958564572688757.74714478434708"
        },
        {
            "ref": "BomRef.10064260186945573.9295742038753935"
        },
        {
            "ref": "BomRef.07070007843852588.7918634161820075"
        },
        {
            "ref": "BomRef.5115547654874881.05707202961673019"
        },
        {
            "ref": "BomRef.12865289530354063.7409058385801865"
        },
        {
            "ref": "BomRef.6625159859935216.6699891159503086"
        },
        {
            "ref": "BomRef.8848340812693124.310430583445651"
        },
        {
            "ref": "BomRef.39058681752921864.4965611636797469"
        },
        {
            "ref": "BomRef.17717660968561055.7017201271770461"
        },
        {
            "ref": "BomRef.7059293712872471.25201883431785255"
        },
        {
            "ref": "BomRef.886306838997562.8658417058213653"
        },
        {
            "ref": "BomRef.4395110251636358.5300268735903221"
        },
        {
            "dependsOn": [
                "BomRef.7482827468261886.5428181743248389",
                "BomRef.41339104680807603.9148211156000156",
                "BomRef.10845249786757905.6295631455225235",
                "BomRef.9447022936118712.9775926813827027",
                "BomRef.933747057254292.192623378477903",
                "BomRef.29585796896308225.4011539855903097",
                "BomRef.4526228399758472.040031838567478606",
                "BomRef.6278394610686211.26598005540029945",
                "BomRef.06792922252167455.1234226959017205",
                "BomRef.2763911425812726.723608253030919",
                "BomRef.11720920793702028.5784137703747054",
                "BomRef.5263196169837733.42411244869411713",
                "BomRef.23781215093069963.10287818011383387",
                "BomRef.4197334068222732.17908345615811538",
                "BomRef.5141660072965649.3699486783653181",
                "BomRef.13926784826767413.5376780774867812",
                "BomRef.8432079752355995.9505224513071566",
                "BomRef.39561889060366373.5619203381473463",
                "BomRef.8528172910485332.8058182491224959",
                "BomRef.9442136822017865.15656170642622735",
                "BomRef.09217663430725431.43424391762302905",
                "BomRef.8868788744703106.4612855729544324",
                "BomRef.8318475582977882.501833798723593",
                "BomRef.178845208752631.3390410028462517",
                "BomRef.0354376712177793.31913294961590466",
                "BomRef.76708726141654.15277658916071246",
                "BomRef.40619986198946834.6387220079417574",
                "BomRef.9200341786545455.085577551566967",
                "BomRef.8390931211341693.7571211030066881",
                "BomRef.846541610123664.047608927424914405",
                "BomRef.9853106168035626.6743913207886603",
                "BomRef.00970284391705556.8624783706278352",
                "BomRef.5125431464776198.628013498778307",
                "BomRef.24798322325711852.3170009239331941",
                "BomRef.9836932812695569.04655833901226114",
                "BomRef.1435770486666108.2777738060654541",
                "BomRef.04522789956784956.23901553539873766",
                "BomRef.48021076054245493.4527105648709856",
                "BomRef.9745197131663971.08089368020740051",
                "BomRef.19998005897320248.321710953977963",
                "BomRef.12382043987595048.4276140553727368"
            ],
            "ref": "pkg:oci/python@3.9-alpine3.13?digest=sha256:a7cbd1e7784a35a098cedbc8681b790d35ff6030a5e13f043185e2465003a040"
        }
    ],
    "metadata": {
        "component": {
            "bom-ref": "pkg:oci/python@3.9-alpine3.13?digest=sha256:a7cbd1e7784a35a098cedbc8681b790d35ff6030a5e13f043185e2465003a040",
            "name": "python",
            "purl": "pkg:oci/python@3.9-alpine3.13?digest=sha256:a7cbd1e7784a35a098cedbc8681b790d35ff6030a5e13f043185e2465003a040",
            "type": "library",
            "version": "3.9-alpine3.13"
        },
        "timestamp": "2025-05-10T11:00:53.813613+00:00",
        "tools": [
            {
                "name": "trivy",
                "vendor": "aquasecurity",
                "version": "unknown"
            }
        ]
    },
    "serialNumber": "urn:uuid:92efb363-29e4-4890-a3a6-9604f254ef79",
    "version": 1,
    "$schema": "http://cyclonedx.org/schema/bom-1.6.schema.json",
    "bomFormat": "CycloneDX",
    "specVersion": "1.6"
}